ClustersFeatures/__init__.py
ClustersFeatures/df_processing.py
ClustersFeatures/imputation.py
ClustersFeatures/index_core.py
ClustersFeatures/raising_errors.py
ClustersFeatures/settings.py
ClustersFeatures/version.py
ClustersFeatures/src/__init__.py
ClustersFeatures/src/_confusion_hypersphere.py
ClustersFeatures/src/_data.py
ClustersFeatures/src/_density.py
ClustersFeatures/src/_graph.py
ClustersFeatures/src/_info.py
ClustersFeatures/src/_score.py
ClustersFeatures/src/_score_index.py
ClustersFeatures/src/_utils.py
ClustersFeatures/src/_verify.py
ClustersFeatures/test/__init__.py
Clusters_Features-1.0.3.dist-info/LICENSE
Clusters_Features-1.0.3.dist-info/METADATA
Clusters_Features-1.0.3.dist-info/WHEEL
Clusters_Features-1.0.3.dist-info/top_level.txt
Clusters_Features-1.0.3.dist-info/RECORD
