Metadata-Version: 2.1
Name: Clusters-Features
Version: 1.0.3
Summary: The Clusters-Features package allows data science users to compute high-level linear algebra operations on any type of data set.
Home-page: https://github.com/Simon-Bertrand
Author: Simon Bertrand
Author-email: simonbertrand.contact@gmail.com
License: UNKNOWN
Project-URL: Cluster-Features, https://github.com/Simon-Bertrand/Clusters-Features
Platform: UNKNOWN
Classifier: Programming Language :: Python :: 3.8
Classifier: License :: OSI Approved :: GNU General Public License v3 (GPLv3)
Classifier: Operating System :: OS Independent
Requires-Python: >=3.8
Requires-Dist: numpy
Requires-Dist: pandas
Requires-Dist: scipy
Requires-Dist: scikit-learn
Requires-Dist: plotly
Requires-Dist: numba
Requires-Dist: umap-learn (>=0.5.1)
Requires-Dist: statsmodels
Requires-Dist: Pillow
